tdgram/__init__.py
tdgram/__meta__.py
tdgram-0.1.0.dist-info/METADATA
tdgram-0.1.0.dist-info/WHEEL
tdgram-0.1.0.dist-info/RECORD
